{
  "index": 349,
  "hash": "86e449604c409e65e7d0a24490a96b0fbcc136515c03acec355e0146e62e277c",
  "source-language": "Greek",
  "sentence": "ὁ μή ἐκ φαίνω ὁ βλέπω γίνομαι πίστις πολύς θυσία",
  "words": [
    "ὁ",
    "μή",
    "ἐκ",
    "φαίνω",
    "ὁ",
    "βλέπω",
    "γίνομαι",
    "πίστις",
    "πολύς",
    "θυσία"
  ],
  "word-count-original": 10,
  "grammatical-notes": {},
  "dictionary-meaning": {},
  "polysemy-log": {},
  "literal-translation": "",
  "main-translation": "",
  "main-translation-explanation": {},
  "rejected-translations": [],
  "rules-applied": [],
  "forensic-confidence": 0
}