{
  "index": 360,
  "hash": "5f1ca7f61be752959f16081e301a96b50ed06518c72b12e826d40a3fbb5a359e",
  "source-language": "Greek",
  "sentence": "τόπος ὅς μέλλω λαμβάνω εἰς κληρονομία καί ἐξέρχομαι μή ἐπίσταμαι",
  "words": [
    "τόπος",
    "ὅς",
    "μέλλω",
    "λαμβάνω",
    "εἰς",
    "κληρονομία",
    "καί",
    "ἐξέρχομαι",
    "μή",
    "ἐπίσταμαι"
  ],
  "word-count-original": 10,
  "grammatical-notes": {},
  "dictionary-meaning": {},
  "polysemy-log": {},
  "literal-translation": "",
  "main-translation": "",
  "main-translation-explanation": {},
  "rejected-translations": [],
  "rules-applied": [],
  "forensic-confidence": 0
}