{
  "index": 7,
  "hash": "84bef5a65e51067e0714ee9e2a0ffdda97faa183f60b722e5c1173cc1618b26c",
  "source-language": "Hebrew",
  "sentence": "הִקְשִׁ֥יבוּ אֵלַ֖/י נְאֻם יְהוָֽה אֲבֽוֹתֵי/כֶ֖ם אַיֵּה הֵ֑ם וְ/הַ֨/נְּבִאִ֔ים הַ/לְ/עוֹלָ֖ם יִֽחְיֽוּ",
  "words": [
    "הִקְשִׁ֥יבוּ",
    "אֵלַ֖/י",
    "נְאֻם",
    "יְהוָֽה",
    "אֲבֽוֹתֵי/כֶ֖ם",
    "אַיֵּה",
    "הֵ֑ם",
    "וְ/הַ֨/נְּבִאִ֔ים",
    "הַ/לְ/עוֹלָ֖ם",
    "יִֽחְיֽוּ"
  ],
  "word-count-original": 10,
  "grammatical-notes": {},
  "dictionary-meaning": {},
  "polysemy-log": {},
  "literal-translation": "",
  "main-translation": "",
  "main-translation-explanation": {},
  "rejected-translations": [],
  "rules-applied": [],
  "forensic-confidence": 0
}