{
  "index": 29,
  "hash": "2a25e8683e99fa0344fde219159d3a67cafe709373da65aa7234cc04dcdab5ff",
  "source-language": "Hebrew",
  "sentence": "וַ/תֵּתַצַּ֥ב אֲחֹת֖/וֹ מֵ/רָחֹ֑ק לְ/דֵעָ֕ה מַה יֵּעָשֶׂ֖ה לֽ/וֹ וַ/תֵּ֤רֶד בַּת פַּרְעֹה֙",
  "words": [
    "וַ/תֵּתַצַּ֥ב",
    "אֲחֹת֖/וֹ",
    "מֵ/רָחֹ֑ק",
    "לְ/דֵעָ֕ה",
    "מַה",
    "יֵּעָשֶׂ֖ה",
    "לֽ/וֹ",
    "וַ/תֵּ֤רֶד",
    "בַּת",
    "פַּרְעֹה֙"
  ],
  "word-count-original": 10,
  "grammatical-notes": {},
  "dictionary-meaning": {},
  "polysemy-log": {},
  "literal-translation": "",
  "main-translation": "",
  "main-translation-explanation": {},
  "rejected-translations": [],
  "rules-applied": [],
  "forensic-confidence": 0
}