{
  "index": 20,
  "hash": "562ab06dec79a24c3f03595b14c8368bd1d020c12b25ca2aaca8b674a7c2b75e",
  "source-language": "Greek",
  "sentence": "λαμβάνω αὐτός εἰς οἰκία καί χαίρω αὐτός μή λέγω ὁ",
  "words": [
    "λαμβάνω",
    "αὐτός",
    "εἰς",
    "οἰκία",
    "καί",
    "χαίρω",
    "αὐτός",
    "μή",
    "λέγω",
    "ὁ"
  ],
  "word-count-original": 10,
  "grammatical-notes": {},
  "dictionary-meaning": {},
  "polysemy-log": {},
  "literal-translation": "",
  "main-translation": "",
  "main-translation-explanation": {},
  "rejected-translations": [],
  "rules-applied": [],
  "forensic-confidence": 0
}