{
  "index": 1446,
  "hash": "91721bcc3a9f9859be427a207441024cf3ad210f08eb0157a975ce99d97feb64",
  "source-language": "Greek",
  "sentence": "κλαίω ὡς οὖν κλαίω παρακύπτω εἰς ὁ μνημεῖον καί θεωρέω",
  "words": [
    "κλαίω",
    "ὡς",
    "οὖν",
    "κλαίω",
    "παρακύπτω",
    "εἰς",
    "ὁ",
    "μνημεῖον",
    "καί",
    "θεωρέω"
  ],
  "word-count-original": 10,
  "grammatical-notes": {},
  "dictionary-meaning": {},
  "polysemy-log": {},
  "literal-translation": "",
  "main-translation": "",
  "main-translation-explanation": {},
  "rejected-translations": [],
  "rules-applied": [],
  "forensic-confidence": 0
}