{
  "index": 40,
  "hash": "b0d58e6a86d475b4eafc1209b4ee97539d015744620d38a0dbaa62a4c39cfee9",
  "source-language": "Hebrew",
  "sentence": "עַמּוֹן֙ כַּֽ/עֲמֹרָ֔ה מִמְשַׁ֥ק חָר֛וּל וּ/מִכְרֵה מֶ֥לַח וּ/שְׁמָמָ֖ה עַד עוֹלָ֑ם שְׁאֵרִ֤ית",
  "words": [
    "עַמּוֹן֙",
    "כַּֽ/עֲמֹרָ֔ה",
    "מִמְשַׁ֥ק",
    "חָר֛וּל",
    "וּ/מִכְרֵה",
    "מֶ֥לַח",
    "וּ/שְׁמָמָ֖ה",
    "עַד",
    "עוֹלָ֑ם",
    "שְׁאֵרִ֤ית"
  ],
  "word-count-original": 10,
  "grammatical-notes": {},
  "dictionary-meaning": {},
  "polysemy-log": {},
  "literal-translation": "",
  "main-translation": "",
  "main-translation-explanation": {},
  "rejected-translations": [],
  "rules-applied": [],
  "forensic-confidence": 0
}