{
  "index": 1535,
  "hash": "d846e11386ebb6a532caaa0ef0f9164d8c708345bbf5cb2063742cce6abcd14f",
  "source-language": "Hebrew",
  "sentence": "עֹשֶׂ֔ה יְהוָ֖ה מַצְלִ֥יחַ בְּ/יָדֽ/וֹ וַ/יִּמְצָ֨א יוֹסֵ֥ף חֵ֛ן בְּ/עֵינָ֖י/ו וַ/יְשָׁ֣רֶת אֹת֑/וֹ",
  "words": [
    "עֹשֶׂ֔ה",
    "יְהוָ֖ה",
    "מַצְלִ֥יחַ",
    "בְּ/יָדֽ/וֹ",
    "וַ/יִּמְצָ֨א",
    "יוֹסֵ֥ף",
    "חֵ֛ן",
    "בְּ/עֵינָ֖י/ו",
    "וַ/יְשָׁ֣רֶת",
    "אֹת֑/וֹ"
  ],
  "word-count-original": 10,
  "grammatical-notes": {},
  "dictionary-meaning": {},
  "polysemy-log": {},
  "literal-translation": "",
  "main-translation": "",
  "main-translation-explanation": {},
  "rejected-translations": [],
  "rules-applied": [],
  "forensic-confidence": 0
}