{
  "index": 1611,
  "hash": "749d61d5c226533e0686e64da8d02e459e86058a0526ee3bfd4957a9ebbb98aa",
  "source-language": "Hebrew",
  "sentence": "אֶחָ֖ד אֲנִ֣י וָ/ה֑וּא אִ֛ישׁ כְּ/פִתְר֥וֹן חֲלֹמ֖/וֹ חָלָֽמְנוּ וְ/שָׁ֨ם אִתָּ֜/נוּ נַ֣עַר",
  "words": [
    "אֶחָ֖ד",
    "אֲנִ֣י",
    "וָ/ה֑וּא",
    "אִ֛ישׁ",
    "כְּ/פִתְר֥וֹן",
    "חֲלֹמ֖/וֹ",
    "חָלָֽמְנוּ",
    "וְ/שָׁ֨ם",
    "אִתָּ֜/נוּ",
    "נַ֣עַר"
  ],
  "word-count-original": 10,
  "grammatical-notes": {},
  "dictionary-meaning": {},
  "polysemy-log": {},
  "literal-translation": "",
  "main-translation": "",
  "main-translation-explanation": {},
  "rejected-translations": [],
  "rules-applied": [],
  "forensic-confidence": 0
}