{
  "index": 480,
  "hash": "31dc1791475f17e270c600881223bd514165caa2bbe298af863adc01cb3fcf94",
  "source-language": "Hebrew",
  "sentence": "לָ/ב֔וֹא וְ/תַרְדֵּמָ֖ה נָפְלָ֣ה עַל אַבְרָ֑ם וְ/הִנֵּ֥ה אֵימָ֛ה חֲשֵׁכָ֥ה גְדֹלָ֖ה נֹפֶ֥לֶת",
  "words": [
    "לָ/ב֔וֹא",
    "וְ/תַרְדֵּמָ֖ה",
    "נָפְלָ֣ה",
    "עַל",
    "אַבְרָ֑ם",
    "וְ/הִנֵּ֥ה",
    "אֵימָ֛ה",
    "חֲשֵׁכָ֥ה",
    "גְדֹלָ֖ה",
    "נֹפֶ֥לֶת"
  ],
  "word-count-original": 10,
  "grammatical-notes": {},
  "dictionary-meaning": {},
  "polysemy-log": {},
  "literal-translation": "",
  "main-translation": "",
  "main-translation-explanation": {},
  "rejected-translations": [],
  "rules-applied": [],
  "forensic-confidence": 0
}