{
  "index": 678,
  "hash": "c3e14d59d205690a0e3e0ed2341432d1831881242234e8a34bf3152c43c29d88",
  "source-language": "Hebrew",
  "sentence": "וַ/יַּ֧עַשׂ יְהוָ֛ה לְ/שָׂרָ֖ה כַּ/אֲשֶׁ֥ר דִּבֵּֽר וַ/תַּהַר֩ וַ/תֵּ֨לֶד שָׂרָ֧ה לְ/אַבְרָהָ֛ם בֵּ֖ן",
  "words": [
    "וַ/יַּ֧עַשׂ",
    "יְהוָ֛ה",
    "לְ/שָׂרָ֖ה",
    "כַּ/אֲשֶׁ֥ר",
    "דִּבֵּֽר",
    "וַ/תַּהַר֩",
    "וַ/תֵּ֨לֶד",
    "שָׂרָ֧ה",
    "לְ/אַבְרָהָ֛ם",
    "בֵּ֖ן"
  ],
  "word-count-original": 10,
  "grammatical-notes": {},
  "dictionary-meaning": {},
  "polysemy-log": {},
  "literal-translation": "",
  "main-translation": "",
  "main-translation-explanation": {},
  "rejected-translations": [],
  "rules-applied": [],
  "forensic-confidence": 0
}