{
  "index": 763,
  "hash": "7b7c7d53e61317c51534e7709d1b625ebcf20d00f027ddd4037e0b4e0a7c8db7",
  "source-language": "Hebrew",
  "sentence": "לֽ/וֹ שְׁמָעֵ֣/נוּ אֲדֹנִ֗/י נְשִׂ֨יא אֱלֹהִ֤ים אַתָּה֙ בְּ/תוֹכֵ֔/נוּ בְּ/מִבְחַ֣ר קְבָרֵ֔י/נוּ קְבֹ֖ר",
  "words": [
    "לֽ/וֹ",
    "שְׁמָעֵ֣/נוּ",
    "אֲדֹנִ֗/י",
    "נְשִׂ֨יא",
    "אֱלֹהִ֤ים",
    "אַתָּה֙",
    "בְּ/תוֹכֵ֔/נוּ",
    "בְּ/מִבְחַ֣ר",
    "קְבָרֵ֔י/נוּ",
    "קְבֹ֖ר"
  ],
  "word-count-original": 10,
  "grammatical-notes": {},
  "dictionary-meaning": {},
  "polysemy-log": {},
  "literal-translation": "",
  "main-translation": "",
  "main-translation-explanation": {},
  "rejected-translations": [],
  "rules-applied": [],
  "forensic-confidence": 0
}