{
  "index": 137,
  "hash": "e6ee7b78b93c3ae58a091f013955691845a308c423ae37a9bd1843527841a45c",
  "source-language": "Hebrew",
  "sentence": "חֶ֨בֶר֙ אֲבִ֣י שׂוֹכ֔וֹ וְ/אֶת יְקֽוּתִיאֵ֖ל אֲבִ֣י זָנ֑וֹחַ וְ/אֵ֗לֶּה בְּנֵי֙ בִּתְיָ֣ה",
  "words": [
    "חֶ֨בֶר֙",
    "אֲבִ֣י",
    "שׂוֹכ֔וֹ",
    "וְ/אֶת",
    "יְקֽוּתִיאֵ֖ל",
    "אֲבִ֣י",
    "זָנ֑וֹחַ",
    "וְ/אֵ֗לֶּה",
    "בְּנֵי֙",
    "בִּתְיָ֣ה"
  ],
  "word-count-original": 10,
  "grammatical-notes": {},
  "dictionary-meaning": {},
  "polysemy-log": {},
  "literal-translation": "",
  "main-translation": "",
  "main-translation-explanation": {},
  "rejected-translations": [],
  "rules-applied": [],
  "forensic-confidence": 0
}