{
  "index": 942,
  "hash": "b3b27183686590c67a566793c3cf334790cc50e5e9957a8b2435b111db9849d5",
  "source-language": "Hebrew",
  "sentence": "עַ֣ל כָּל אֹצְר֤וֹת הַ/קֳּדָשִׁים֙ אֲשֶׁ֨ר הִקְדִּ֜ישׁ דָּוִ֣יד הַ/מֶּ֗לֶךְ וְ/רָאשֵׁ֧י הָ/אָב֛וֹת",
  "words": [
    "עַ֣ל",
    "כָּל",
    "אֹצְר֤וֹת",
    "הַ/קֳּדָשִׁים֙",
    "אֲשֶׁ֨ר",
    "הִקְדִּ֜ישׁ",
    "דָּוִ֣יד",
    "הַ/מֶּ֗לֶךְ",
    "וְ/רָאשֵׁ֧י",
    "הָ/אָב֛וֹת"
  ],
  "word-count-original": 10,
  "grammatical-notes": {},
  "dictionary-meaning": {},
  "polysemy-log": {},
  "literal-translation": "",
  "main-translation": "",
  "main-translation-explanation": {},
  "rejected-translations": [],
  "rules-applied": [],
  "forensic-confidence": 0
}