{
  "index": 507,
  "hash": "5354096b09c10515d7c7e8d51aaf4ecc3888904416977d0bb0380e0cf0ff107b",
  "source-language": "Hebrew",
  "sentence": "א֖וֹ בְּ/כָל מְלֶ֥אכֶת עֽוֹר וְ/הָיָ֨ה הַ/נֶּ֜גַע יְרַקְרַ֣ק א֣וֹ אֲדַמְדָּ֗ם בַּ/בֶּגֶד֩",
  "words": [
    "א֖וֹ",
    "בְּ/כָל",
    "מְלֶ֥אכֶת",
    "עֽוֹר",
    "וְ/הָיָ֨ה",
    "הַ/נֶּ֜גַע",
    "יְרַקְרַ֣ק",
    "א֣וֹ",
    "אֲדַמְדָּ֗ם",
    "בַּ/בֶּגֶד֩"
  ],
  "word-count-original": 10,
  "grammatical-notes": {},
  "dictionary-meaning": {},
  "polysemy-log": {},
  "literal-translation": "",
  "main-translation": "",
  "main-translation-explanation": {},
  "rejected-translations": [],
  "rules-applied": [],
  "forensic-confidence": 0
}