{
  "index": 223,
  "hash": "ca67eb1fa2272afedd644165c7ad9a062f6b17d29b87621fc35d6fa561846182",
  "source-language": "Greek",
  "sentence": "ὁ σημεῖον οὗτος ὁ ἴασις ἀπολύω δέ ἔρχομαι πρός ὁ",
  "words": [
    "ὁ",
    "σημεῖον",
    "οὗτος",
    "ὁ",
    "ἴασις",
    "ἀπολύω",
    "δέ",
    "ἔρχομαι",
    "πρός",
    "ὁ"
  ],
  "word-count-original": 10,
  "grammatical-notes": {},
  "dictionary-meaning": {},
  "polysemy-log": {},
  "literal-translation": "",
  "main-translation": "",
  "main-translation-explanation": {},
  "rejected-translations": [],
  "rules-applied": [],
  "forensic-confidence": 0
}