{
  "index": 22,
  "hash": "871c1cf40276d439137e29e1bddc5d511999c3667a144dc47c7018b273f9b398",
  "source-language": "Greek",
  "sentence": "καί ἐν ὁ λοιπός ἔθνος Ἕλλην τέ καί βάρβαρος σοφός",
  "words": [
    "καί",
    "ἐν",
    "ὁ",
    "λοιπός",
    "ἔθνος",
    "Ἕλλην",
    "τέ",
    "καί",
    "βάρβαρος",
    "σοφός"
  ],
  "word-count-original": 10,
  "grammatical-notes": {},
  "dictionary-meaning": {},
  "polysemy-log": {},
  "literal-translation": "",
  "main-translation": "",
  "main-translation-explanation": {},
  "rejected-translations": [],
  "rules-applied": [],
  "forensic-confidence": 0
}