{
  "index": 351,
  "hash": "fb82ed2678080325a8f039c2f840624c25206c69dc1005b15c62403a9347d074",
  "source-language": "Greek",
  "sentence": "πνεῦμα συναντιλαμβάνομαι ὁ ἀσθένεια ἐγώ ὁ γάρ τίς προσεύχομαι καθό",
  "words": [
    "πνεῦμα",
    "συναντιλαμβάνομαι",
    "ὁ",
    "ἀσθένεια",
    "ἐγώ",
    "ὁ",
    "γάρ",
    "τίς",
    "προσεύχομαι",
    "καθό"
  ],
  "word-count-original": 10,
  "grammatical-notes": {},
  "dictionary-meaning": {},
  "polysemy-log": {},
  "literal-translation": "",
  "main-translation": "",
  "main-translation-explanation": {},
  "rejected-translations": [],
  "rules-applied": [],
  "forensic-confidence": 0
}