{
  "index": 641,
  "hash": "69b838b213fc066ec68ffca45fa38aa9b995321202057fc333802a8cbe585574",
  "source-language": "Greek",
  "sentence": "ὁ προσφορά ὁ ἔθνος εὐπρόσδεκτος ἁγιάζω ἐν πνεῦμα ἅγιος ἔχω",
  "words": [
    "ὁ",
    "προσφορά",
    "ὁ",
    "ἔθνος",
    "εὐπρόσδεκτος",
    "ἁγιάζω",
    "ἐν",
    "πνεῦμα",
    "ἅγιος",
    "ἔχω"
  ],
  "word-count-original": 10,
  "grammatical-notes": {},
  "dictionary-meaning": {},
  "polysemy-log": {},
  "literal-translation": "",
  "main-translation": "",
  "main-translation-explanation": {},
  "rejected-translations": [],
  "rules-applied": [],
  "forensic-confidence": 0
}