{
  "index": 202,
  "hash": "a299cf05ddf1bf7557aff1611edd2562d277d9c1b20a5bbe9be51f992679c866",
  "source-language": "Hebrew",
  "sentence": "נִלְחֲמוּ֙ מַלְכֵ֣י כְנַ֔עַן בְּ/תַעְנַ֖ךְ עַל מֵ֣י מְגִדּ֑וֹ בֶּ֥צַע כֶּ֖סֶף לֹ֥א",
  "words": [
    "נִלְחֲמוּ֙",
    "מַלְכֵ֣י",
    "כְנַ֔עַן",
    "בְּ/תַעְנַ֖ךְ",
    "עַל",
    "מֵ֣י",
    "מְגִדּ֑וֹ",
    "בֶּ֥צַע",
    "כֶּ֖סֶף",
    "לֹ֥א"
  ],
  "word-count-original": 10,
  "grammatical-notes": {},
  "dictionary-meaning": {},
  "polysemy-log": {},
  "literal-translation": "",
  "main-translation": "",
  "main-translation-explanation": {},
  "rejected-translations": [],
  "rules-applied": [],
  "forensic-confidence": 0
}