{
  "index": 191,
  "hash": "184eb53f2605cb2516c0ee46f8df1ce1171053efd1f038d45e79b1490157e386",
  "source-language": "Hebrew",
  "sentence": "אַל תְּשַׁלְּח֤וּ אֹת/וֹ֙ רֵיקָ֔ם כִּֽי הָשֵׁ֥ב תָּשִׁ֛יבוּ ל֖/וֹ אָשָׁ֑ם אָ֤ז",
  "words": [
    "אַל",
    "תְּשַׁלְּח֤וּ",
    "אֹת/וֹ֙",
    "רֵיקָ֔ם",
    "כִּֽי",
    "הָשֵׁ֥ב",
    "תָּשִׁ֛יבוּ",
    "ל֖/וֹ",
    "אָשָׁ֑ם",
    "אָ֤ז"
  ],
  "word-count-original": 10,
  "grammatical-notes": {},
  "dictionary-meaning": {},
  "polysemy-log": {},
  "literal-translation": "",
  "main-translation": "",
  "main-translation-explanation": {},
  "rejected-translations": [],
  "rules-applied": [],
  "forensic-confidence": 0
}