{
  "index": 290,
  "hash": "525f22cd8e25b2fc7870030f62549be958f2b111b1066e7106daccd1fcf00b95",
  "source-language": "Hebrew",
  "sentence": "בְּ/הַר אֶפְרַ֛יִם וַ/יַּעֲבֹ֥ר בְּ/אֶֽרֶץ שָׁלִ֖שָׁה וְ/לֹ֣א מָצָ֑אוּ וַ/יַּעַבְר֤וּ בְ/אֶֽרֶץ שַׁעֲלִים֙",
  "words": [
    "בְּ/הַר",
    "אֶפְרַ֛יִם",
    "וַ/יַּעֲבֹ֥ר",
    "בְּ/אֶֽרֶץ",
    "שָׁלִ֖שָׁה",
    "וְ/לֹ֣א",
    "מָצָ֑אוּ",
    "וַ/יַּעַבְר֤וּ",
    "בְ/אֶֽרֶץ",
    "שַׁעֲלִים֙"
  ],
  "word-count-original": 10,
  "grammatical-notes": {},
  "dictionary-meaning": {},
  "polysemy-log": {},
  "literal-translation": "",
  "main-translation": "",
  "main-translation-explanation": {},
  "rejected-translations": [],
  "rules-applied": [],
  "forensic-confidence": 0
}