{
  "index": 999,
  "hash": "4437ab0d3c15c91179e3fc3fdc0adb66f9064119830874c72d777ddc3a81215e",
  "source-language": "Hebrew",
  "sentence": "תִּירָ֗א כִּ֠י לֹ֤א תִֽמְצָאֲ/ךָ֙ יַ֚ד שָׁא֣וּל אָבִ֔/י וְ/אַתָּה֙ תִּמְלֹ֣ךְ עַל",
  "words": [
    "תִּירָ֗א",
    "כִּ֠י",
    "לֹ֤א",
    "תִֽמְצָאֲ/ךָ֙",
    "יַ֚ד",
    "שָׁא֣וּל",
    "אָבִ֔/י",
    "וְ/אַתָּה֙",
    "תִּמְלֹ֣ךְ",
    "עַל"
  ],
  "word-count-original": 10,
  "grammatical-notes": {},
  "dictionary-meaning": {},
  "polysemy-log": {},
  "literal-translation": "",
  "main-translation": "",
  "main-translation-explanation": {},
  "rejected-translations": [],
  "rules-applied": [],
  "forensic-confidence": 0
}