{
  "index": 69,
  "hash": "a57fa810fe9f8130b2c7062983d70a8a6da878493d302fd4e30e4bdc31952754",
  "source-language": "Greek",
  "sentence": "μένω ὅς ἀπό ἀρχή ἀκούω καί σύ ἐν ὁ υἱός",
  "words": [
    "μένω",
    "ὅς",
    "ἀπό",
    "ἀρχή",
    "ἀκούω",
    "καί",
    "σύ",
    "ἐν",
    "ὁ",
    "υἱός"
  ],
  "word-count-original": 10,
  "grammatical-notes": {},
  "dictionary-meaning": {},
  "polysemy-log": {},
  "literal-translation": "",
  "main-translation": "",
  "main-translation-explanation": {},
  "rejected-translations": [],
  "rules-applied": [],
  "forensic-confidence": 0
}