{
  "index": 44,
  "hash": "d254455249246c438da7a3bfb35069107a63e61f89ff931549d0e73607b167f5",
  "source-language": "Hebrew",
  "sentence": "שׁוֹפָ֖ר בְּ/צִיּ֑וֹן קַדְּשׁוּ צ֖וֹם קִרְא֥וּ עֲצָרָֽה אִסְפוּ עָ֞ם קַדְּשׁ֤וּ קָהָל֙",
  "words": [
    "שׁוֹפָ֖ר",
    "בְּ/צִיּ֑וֹן",
    "קַדְּשׁוּ",
    "צ֖וֹם",
    "קִרְא֥וּ",
    "עֲצָרָֽה",
    "אִסְפוּ",
    "עָ֞ם",
    "קַדְּשׁ֤וּ",
    "קָהָל֙"
  ],
  "word-count-original": 10,
  "grammatical-notes": {},
  "dictionary-meaning": {},
  "polysemy-log": {},
  "literal-translation": "",
  "main-translation": "",
  "main-translation-explanation": {},
  "rejected-translations": [],
  "rules-applied": [],
  "forensic-confidence": 0
}