{
  "index": 24,
  "hash": "04bd61b6bb9c28a356b6e141cadc18a103f50d23c1eafef26ee49e5a81de9c1e",
  "source-language": "Hebrew",
  "sentence": "לְ/מַטֵּ֣ה גָ֑ד חֲמִשָּׁ֤ה וְ/אַרְבָּעִים֙ אֶ֔לֶף וְ/שֵׁ֥שׁ מֵא֖וֹת וַ/חֲמִשִּֽׁים לִ/בְנֵ֣י יְהוּדָ֔ה",
  "words": [
    "לְ/מַטֵּ֣ה",
    "גָ֑ד",
    "חֲמִשָּׁ֤ה",
    "וְ/אַרְבָּעִים֙",
    "אֶ֔לֶף",
    "וְ/שֵׁ֥שׁ",
    "מֵא֖וֹת",
    "וַ/חֲמִשִּֽׁים",
    "לִ/בְנֵ֣י",
    "יְהוּדָ֔ה"
  ],
  "word-count-original": 10,
  "grammatical-notes": {},
  "dictionary-meaning": {},
  "polysemy-log": {},
  "literal-translation": "",
  "main-translation": "",
  "main-translation-explanation": {},
  "rejected-translations": [],
  "rules-applied": [],
  "forensic-confidence": 0
}