{
  "index": 325,
  "hash": "0b597e10654dabfd179805c544041f8360069b28dd31ca091e05913bd44ec6b4",
  "source-language": "Hebrew",
  "sentence": "בַּ/יּוֹם֙ הַ/שֵּׁנִ֔י הִקְרִ֖יב נְתַנְאֵ֣ל בֶּן צוּעָ֑ר נְשִׂ֖יא יִשָּׂשכָֽר הִקְרִ֨ב אֶת",
  "words": [
    "בַּ/יּוֹם֙",
    "הַ/שֵּׁנִ֔י",
    "הִקְרִ֖יב",
    "נְתַנְאֵ֣ל",
    "בֶּן",
    "צוּעָ֑ר",
    "נְשִׂ֖יא",
    "יִשָּׂשכָֽר",
    "הִקְרִ֨ב",
    "אֶת"
  ],
  "word-count-original": 10,
  "grammatical-notes": {},
  "dictionary-meaning": {},
  "polysemy-log": {},
  "literal-translation": "",
  "main-translation": "",
  "main-translation-explanation": {},
  "rejected-translations": [],
  "rules-applied": [],
  "forensic-confidence": 0
}