{
  "index": 707,
  "hash": "2320d4e8bc875fbbdf5725e593fe15d28053baf7f60c2d3cef6387d45b3e6fa2",
  "source-language": "Hebrew",
  "sentence": "בֶּן הַ/בָּקָר֙ מִנְחָ֔ה סֹ֖לֶת שְׁלֹשָׁ֣ה עֶשְׂרֹנִ֑ים בָּל֥וּל בַּ/שֶּׁ֖מֶן חֲצִ֥י הַ/הִֽין",
  "words": [
    "בֶּן",
    "הַ/בָּקָר֙",
    "מִנְחָ֔ה",
    "סֹ֖לֶת",
    "שְׁלֹשָׁ֣ה",
    "עֶשְׂרֹנִ֑ים",
    "בָּל֥וּל",
    "בַּ/שֶּׁ֖מֶן",
    "חֲצִ֥י",
    "הַ/הִֽין"
  ],
  "word-count-original": 10,
  "grammatical-notes": {},
  "dictionary-meaning": {},
  "polysemy-log": {},
  "literal-translation": "",
  "main-translation": "",
  "main-translation-explanation": {},
  "rejected-translations": [],
  "rules-applied": [],
  "forensic-confidence": 0
}