{
  "index": 110,
  "hash": "95a73bcf2d2c117c3bc1e83368ffc434d9262a880c1aaa7c6b0c776b512ddb7d",
  "source-language": "Hebrew",
  "sentence": "הָ/אֵ֗לֶּה וְ/לֹ֤א יִשְׁמְעוּ/ן֙ לְ/קֹלֶ֔/ךָ וְ/לָקַחְתָּ֙ מִ/מֵּימֵ֣י הַ/יְאֹ֔ר וְ/שָׁפַכְתָּ֖ הַ/יַּבָּשָׁ֑ה וְ/הָי֤וּ",
  "words": [
    "הָ/אֵ֗לֶּה",
    "וְ/לֹ֤א",
    "יִשְׁמְעוּ/ן֙",
    "לְ/קֹלֶ֔/ךָ",
    "וְ/לָקַחְתָּ֙",
    "מִ/מֵּימֵ֣י",
    "הַ/יְאֹ֔ר",
    "וְ/שָׁפַכְתָּ֖",
    "הַ/יַּבָּשָׁ֑ה",
    "וְ/הָי֤וּ"
  ],
  "word-count-original": 10,
  "grammatical-notes": {},
  "dictionary-meaning": {},
  "polysemy-log": {},
  "literal-translation": "",
  "main-translation": "",
  "main-translation-explanation": {},
  "rejected-translations": [],
  "rules-applied": [],
  "forensic-confidence": 0
}