{
  "index": 533,
  "hash": "8dbec983f3810156fe191376f7b8f780e17db7767a5ca36375597e07c22a82ee",
  "source-language": "Greek",
  "sentence": "παρακαλέω ἐν ὁ παράκλησις ὁ μεταδίδωμι ἐν ἁπλότης ὁ προΐστημι",
  "words": [
    "παρακαλέω",
    "ἐν",
    "ὁ",
    "παράκλησις",
    "ὁ",
    "μεταδίδωμι",
    "ἐν",
    "ἁπλότης",
    "ὁ",
    "προΐστημι"
  ],
  "word-count-original": 10,
  "grammatical-notes": {},
  "dictionary-meaning": {},
  "polysemy-log": {},
  "literal-translation": "",
  "main-translation": "",
  "main-translation-explanation": {},
  "rejected-translations": [],
  "rules-applied": [],
  "forensic-confidence": 0
}