{
  "index": 1477,
  "hash": "3054f69fbd4994f34d9db3f843d3501c70fb219687bc77ec85c4360b37665a3c",
  "source-language": "Hebrew",
  "sentence": "מַה בֶּ֗צַע כִּ֤י נַהֲרֹג֙ אֶת אָחִ֔י/נוּ וְ/כִסִּ֖ינוּ אֶת דָּמֽ/וֹ לְכ֞וּ",
  "words": [
    "מַה",
    "בֶּ֗צַע",
    "כִּ֤י",
    "נַהֲרֹג֙",
    "אֶת",
    "אָחִ֔י/נוּ",
    "וְ/כִסִּ֖ינוּ",
    "אֶת",
    "דָּמֽ/וֹ",
    "לְכ֞וּ"
  ],
  "word-count-original": 10,
  "grammatical-notes": {},
  "dictionary-meaning": {},
  "polysemy-log": {},
  "literal-translation": "",
  "main-translation": "",
  "main-translation-explanation": {},
  "rejected-translations": [],
  "rules-applied": [],
  "forensic-confidence": 0
}