{
  "index": 313,
  "hash": "027d541b7e1563d2ac96237b68367a8bd3193d5298652f2803faf7ba66971d2e",
  "source-language": "Hebrew",
  "sentence": "וָ/יָ֑פֶת וַ/יִּוָּלְד֥וּ לָ/הֶ֛ם בָּנִ֖ים אַחַ֥ר הַ/מַּבּֽוּל בְּנֵ֣י יֶ֔פֶת גֹּ֣מֶר וּ/מָג֔וֹג",
  "words": [
    "וָ/יָ֑פֶת",
    "וַ/יִּוָּלְד֥וּ",
    "לָ/הֶ֛ם",
    "בָּנִ֖ים",
    "אַחַ֥ר",
    "הַ/מַּבּֽוּל",
    "בְּנֵ֣י",
    "יֶ֔פֶת",
    "גֹּ֣מֶר",
    "וּ/מָג֔וֹג"
  ],
  "word-count-original": 10,
  "grammatical-notes": {},
  "dictionary-meaning": {},
  "polysemy-log": {},
  "literal-translation": "",
  "main-translation": "",
  "main-translation-explanation": {},
  "rejected-translations": [],
  "rules-applied": [],
  "forensic-confidence": 0
}