{
  "index": 252,
  "hash": "1bf08fad73832a92635ba871594c1316a7b2fe3ee53fefb0861e24db28e512a9",
  "source-language": "Hebrew",
  "sentence": "גְּדוֹלִֽים יֵ֣שׁ רָעָ֔ה רָאִ֖יתִי תַּ֣חַת הַ/שָּׁ֑מֶשׁ כִּ/שְׁגָגָ֕ה שֶׁ/יֹּצָ֖א מִ/לִּ/פְנֵ֥י הַ/שַּׁלִּֽיט",
  "words": [
    "גְּדוֹלִֽים",
    "יֵ֣שׁ",
    "רָעָ֔ה",
    "רָאִ֖יתִי",
    "תַּ֣חַת",
    "הַ/שָּׁ֑מֶשׁ",
    "כִּ/שְׁגָגָ֕ה",
    "שֶׁ/יֹּצָ֖א",
    "מִ/לִּ/פְנֵ֥י",
    "הַ/שַּׁלִּֽיט"
  ],
  "word-count-original": 10,
  "grammatical-notes": {},
  "dictionary-meaning": {},
  "polysemy-log": {},
  "literal-translation": "",
  "main-translation": "",
  "main-translation-explanation": {},
  "rejected-translations": [],
  "rules-applied": [],
  "forensic-confidence": 0
}