{
  "index": 71,
  "hash": "3a9cdbed7a7252b72e62d9e619b89e1b2a7d0aec2932d66764b0e3246b5261ab",
  "source-language": "Hebrew",
  "sentence": "וְ/עַד סֽוֹף יָדַ֕עְתִּי כִּ֛י אֵ֥ין ט֖וֹב בָּ֑/ם כִּ֣י אִם לִ/שְׂמ֔וֹחַ",
  "words": [
    "וְ/עַד",
    "סֽוֹף",
    "יָדַ֕עְתִּי",
    "כִּ֛י",
    "אֵ֥ין",
    "ט֖וֹב",
    "בָּ֑/ם",
    "כִּ֣י",
    "אִם",
    "לִ/שְׂמ֔וֹחַ"
  ],
  "word-count-original": 10,
  "grammatical-notes": {},
  "dictionary-meaning": {},
  "polysemy-log": {},
  "literal-translation": "",
  "main-translation": "",
  "main-translation-explanation": {},
  "rejected-translations": [],
  "rules-applied": [],
  "forensic-confidence": 0
}