{
  "index": 300,
  "hash": "4d4486a09af3c25b30c2582d0ee72b3ceaa5e8910fa65c68973ac4afc0e3e157",
  "source-language": "Hebrew",
  "sentence": "וְ/הִ֣יא הַ/סִּ֑יר וְ/אֶתְ/כֶ֖ם הוֹצִ֥יא מִ/תּוֹכָֽ/הּ חֶ֖רֶב יְרֵאתֶ֑ם וְ/חֶ֨רֶב֙ אָבִ֣יא עֲלֵי/כֶ֔ם",
  "words": [
    "וְ/הִ֣יא",
    "הַ/סִּ֑יר",
    "וְ/אֶתְ/כֶ֖ם",
    "הוֹצִ֥יא",
    "מִ/תּוֹכָֽ/הּ",
    "חֶ֖רֶב",
    "יְרֵאתֶ֑ם",
    "וְ/חֶ֨רֶב֙",
    "אָבִ֣יא",
    "עֲלֵי/כֶ֔ם"
  ],
  "word-count-original": 10,
  "grammatical-notes": {},
  "dictionary-meaning": {},
  "polysemy-log": {},
  "literal-translation": "",
  "main-translation": "",
  "main-translation-explanation": {},
  "rejected-translations": [],
  "rules-applied": [],
  "forensic-confidence": 0
}