{
  "index": 344,
  "hash": "bb89f8c8036c765afdd55fd0457956b04d64fc6b391ccffdf732ef333b260b63",
  "source-language": "Hebrew",
  "sentence": "וְ/שָׁ֥ם יָמֽוּת וְ/כֹל֩ אֲשֶׁ֨ר סְבִיבֹתָ֥י/ו עזר/ה עֶזְר֛/וֹ וְ/כָל אֲגַפָּ֖י/ו אֱזָרֶ֣ה",
  "words": [
    "וְ/שָׁ֥ם",
    "יָמֽוּת",
    "וְ/כֹל֩",
    "אֲשֶׁ֨ר",
    "סְבִיבֹתָ֥י/ו",
    "עזר/ה",
    "עֶזְר֛/וֹ",
    "וְ/כָל",
    "אֲגַפָּ֖י/ו",
    "אֱזָרֶ֣ה"
  ],
  "word-count-original": 10,
  "grammatical-notes": {},
  "dictionary-meaning": {},
  "polysemy-log": {},
  "literal-translation": "",
  "main-translation": "",
  "main-translation-explanation": {},
  "rejected-translations": [],
  "rules-applied": [],
  "forensic-confidence": 0
}