{
  "index": 452,
  "hash": "c1d23a9a5762a9a727f958490bdd117faa38b5877924a09bfe0321b344506732",
  "source-language": "Hebrew",
  "sentence": "לֵ֣ץ שְׁמ֑/וֹ ע֝וֹשֶׂ֗ה בְּ/עֶבְרַ֥ת זָדֽוֹן תַּאֲוַ֣ת עָצֵ֣ל תְּמִיתֶ֑/נּוּ כִּֽי מֵאֲנ֖וּ",
  "words": [
    "לֵ֣ץ",
    "שְׁמ֑/וֹ",
    "ע֝וֹשֶׂ֗ה",
    "בְּ/עֶבְרַ֥ת",
    "זָדֽוֹן",
    "תַּאֲוַ֣ת",
    "עָצֵ֣ל",
    "תְּמִיתֶ֑/נּוּ",
    "כִּֽי",
    "מֵאֲנ֖וּ"
  ],
  "word-count-original": 10,
  "grammatical-notes": {},
  "dictionary-meaning": {},
  "polysemy-log": {},
  "literal-translation": "",
  "main-translation": "",
  "main-translation-explanation": {},
  "rejected-translations": [],
  "rules-applied": [],
  "forensic-confidence": 0
}