{
  "index": 1210,
  "hash": "27a64450ced9b7e234064b01ce67fcabb4f8ae5eb522b02e746d559f0d0cc5cd",
  "source-language": "Hebrew",
  "sentence": "אִ֣ישׁ אוֹ אִשָּׁ֞ה א֧וֹ מִשְׁפָּחָ֣ה אוֹ שֵׁ֗בֶט אֲשֶׁר֩ לְבָב֨/וֹ פֹנֶ֤ה",
  "words": [
    "אִ֣ישׁ",
    "אוֹ",
    "אִשָּׁ֞ה",
    "א֧וֹ",
    "מִשְׁפָּחָ֣ה",
    "אוֹ",
    "שֵׁ֗בֶט",
    "אֲשֶׁר֩",
    "לְבָב֨/וֹ",
    "פֹנֶ֤ה"
  ],
  "word-count-original": 10,
  "grammatical-notes": {},
  "dictionary-meaning": {},
  "polysemy-log": {},
  "literal-translation": "",
  "main-translation": "",
  "main-translation-explanation": {},
  "rejected-translations": [],
  "rules-applied": [],
  "forensic-confidence": 0
}