{
  "index": 130,
  "hash": "121052199529d074851d5c1f151454b934a9e18776230e0c6c3d30777feefe50",
  "source-language": "Hebrew",
  "sentence": "לֹ֣א נָטָ֑ה וַ/יָּ֤נָס יוֹאָב֙ אֶל אֹ֣הֶל יְהוָ֔ה וַֽ/יַּחֲזֵ֖ק בְּ/קַרְנ֥וֹת הַ/מִּזְבֵּֽחַ",
  "words": [
    "לֹ֣א",
    "נָטָ֑ה",
    "וַ/יָּ֤נָס",
    "יוֹאָב֙",
    "אֶל",
    "אֹ֣הֶל",
    "יְהוָ֔ה",
    "וַֽ/יַּחֲזֵ֖ק",
    "בְּ/קַרְנ֥וֹת",
    "הַ/מִּזְבֵּֽחַ"
  ],
  "word-count-original": 10,
  "grammatical-notes": {},
  "dictionary-meaning": {},
  "polysemy-log": {},
  "literal-translation": "",
  "main-translation": "",
  "main-translation-explanation": {},
  "rejected-translations": [],
  "rules-applied": [],
  "forensic-confidence": 0
}