{
  "index": 396,
  "hash": "2e251bbc4ae23d8feed8d7bb391084de02a72b6dda1c9875955bb42da9d0cbaf",
  "source-language": "Hebrew",
  "sentence": "אֶת שְׁתֵּי֙ גֻּלֹּ֣ת הַ/כֹּֽתָרֹ֔ת אֲשֶׁ֖ר עַל רֹ֥אשׁ הָ/עַמּוּדִֽים וְ/אֶת הָ/רִמֹּנִ֛ים",
  "words": [
    "אֶת",
    "שְׁתֵּי֙",
    "גֻּלֹּ֣ת",
    "הַ/כֹּֽתָרֹ֔ת",
    "אֲשֶׁ֖ר",
    "עַל",
    "רֹ֥אשׁ",
    "הָ/עַמּוּדִֽים",
    "וְ/אֶת",
    "הָ/רִמֹּנִ֛ים"
  ],
  "word-count-original": 10,
  "grammatical-notes": {},
  "dictionary-meaning": {},
  "polysemy-log": {},
  "literal-translation": "",
  "main-translation": "",
  "main-translation-explanation": {},
  "rejected-translations": [],
  "rules-applied": [],
  "forensic-confidence": 0
}