{
  "index": 139,
  "hash": "e7501dcf18eb93af167fc17ae092913e961a4db4f9ce9186f69829b5e85a1c4e",
  "source-language": "Greek",
  "sentence": "Τυχικός ὁ ἀγαπητός ἀδελφός καί πιστός διάκονος καί σύνδουλος ἐν",
  "words": [
    "Τυχικός",
    "ὁ",
    "ἀγαπητός",
    "ἀδελφός",
    "καί",
    "πιστός",
    "διάκονος",
    "καί",
    "σύνδουλος",
    "ἐν"
  ],
  "word-count-original": 10,
  "grammatical-notes": {},
  "dictionary-meaning": {},
  "polysemy-log": {},
  "literal-translation": "",
  "main-translation": "",
  "main-translation-explanation": {},
  "rejected-translations": [],
  "rules-applied": [],
  "forensic-confidence": 0
}