{
  "index": 406,
  "hash": "990da01d3066316012d584fd0be3c51cd6750cfee85246c056e360176103b804",
  "source-language": "Hebrew",
  "sentence": "מוֹרִישָׁ֣/ם מִ/פָּנֶ֔י/ךָ וּ/לְמַ֜עַן הָקִ֣ים אֶת הַ/דָּבָ֗ר אֲשֶׁ֨ר נִשְׁבַּ֤ע יְהוָה֙ לַ/אֲבֹתֶ֔י/ךָ",
  "words": [
    "מוֹרִישָׁ֣/ם",
    "מִ/פָּנֶ֔י/ךָ",
    "וּ/לְמַ֜עַן",
    "הָקִ֣ים",
    "אֶת",
    "הַ/דָּבָ֗ר",
    "אֲשֶׁ֨ר",
    "נִשְׁבַּ֤ע",
    "יְהוָה֙",
    "לַ/אֲבֹתֶ֔י/ךָ"
  ],
  "word-count-original": 10,
  "grammatical-notes": {},
  "dictionary-meaning": {},
  "polysemy-log": {},
  "literal-translation": "",
  "main-translation": "",
  "main-translation-explanation": {},
  "rejected-translations": [],
  "rules-applied": [],
  "forensic-confidence": 0
}