{
  "index": 1084,
  "hash": "4c0611a552f7b00e4ee5534542924aa5a1ae7045091fad505d4dd2339223d116",
  "source-language": "Hebrew",
  "sentence": "עַל מִצְרַ֔יִם וּ/מָלְא֥וּ אֶת הָ/אָ֖רֶץ חָלָֽל וְ/נָתַתִּ֤י יְאֹרִים֙ חָֽרָבָ֔ה וּ/מָכַרְתִּ֥י",
  "words": [
    "עַל",
    "מִצְרַ֔יִם",
    "וּ/מָלְא֥וּ",
    "אֶת",
    "הָ/אָ֖רֶץ",
    "חָלָֽל",
    "וְ/נָתַתִּ֤י",
    "יְאֹרִים֙",
    "חָֽרָבָ֔ה",
    "וּ/מָכַרְתִּ֥י"
  ],
  "word-count-original": 10,
  "grammatical-notes": {},
  "dictionary-meaning": {},
  "polysemy-log": {},
  "literal-translation": "",
  "main-translation": "",
  "main-translation-explanation": {},
  "rejected-translations": [],
  "rules-applied": [],
  "forensic-confidence": 0
}