{
  "index": 1085,
  "hash": "fcbb9811158eeed8e0f1807df3a4e9ad69ee58308a8d0676b86d83ae3bde2a29",
  "source-language": "Hebrew",
  "sentence": "אֶת הָ/אָ֖רֶץ בְּ/יַד רָעִ֑ים וַ/הֲשִׁמֹּתִ֞י אֶ֤רֶץ וּ/מְלֹאָ/הּ֙ בְּ/יַד זָרִ֔ים אֲנִ֥י",
  "words": [
    "אֶת",
    "הָ/אָ֖רֶץ",
    "בְּ/יַד",
    "רָעִ֑ים",
    "וַ/הֲשִׁמֹּתִ֞י",
    "אֶ֤רֶץ",
    "וּ/מְלֹאָ/הּ֙",
    "בְּ/יַד",
    "זָרִ֔ים",
    "אֲנִ֥י"
  ],
  "word-count-original": 10,
  "grammatical-notes": {},
  "dictionary-meaning": {},
  "polysemy-log": {},
  "literal-translation": "",
  "main-translation": "",
  "main-translation-explanation": {},
  "rejected-translations": [],
  "rules-applied": [],
  "forensic-confidence": 0
}