{
  "index": 1229,
  "hash": "4fa6019334fa94c04fec7d37c5584326f9f15f188946a0fff252e318f1939d35",
  "source-language": "Hebrew",
  "sentence": "וְ/יִרְמְיָ֣הוּ הַ/נָּבִ֗יא הָיָ֤ה כָלוּא֙ בַּ/חֲצַ֣ר הַ/מַּטָּרָ֔ה אֲשֶׁ֖ר בֵּֽית מֶ֥לֶךְ יְהוּדָֽה",
  "words": [
    "וְ/יִרְמְיָ֣הוּ",
    "הַ/נָּבִ֗יא",
    "הָיָ֤ה",
    "כָלוּא֙",
    "בַּ/חֲצַ֣ר",
    "הַ/מַּטָּרָ֔ה",
    "אֲשֶׁ֖ר",
    "בֵּֽית",
    "מֶ֥לֶךְ",
    "יְהוּדָֽה"
  ],
  "word-count-original": 10,
  "grammatical-notes": {},
  "dictionary-meaning": {},
  "polysemy-log": {},
  "literal-translation": "",
  "main-translation": "",
  "main-translation-explanation": {},
  "rejected-translations": [],
  "rules-applied": [],
  "forensic-confidence": 0
}