{
  "index": 767,
  "hash": "fd9ac1d69232bf61896247bc4decc246478acc26b2278a1fb74c662de3f70f63",
  "source-language": "Hebrew",
  "sentence": "מִשְׁפָּ֔ט וְ/הַצִּ֥ילוּ גָז֖וּל מִ/יַּ֣ד עוֹשֵׁ֑ק פֶּן תֵּצֵ֨א כָ/אֵ֜שׁ חֲמָתִ֗/י וּ/בָעֲרָה֙",
  "words": [
    "מִשְׁפָּ֔ט",
    "וְ/הַצִּ֥ילוּ",
    "גָז֖וּל",
    "מִ/יַּ֣ד",
    "עוֹשֵׁ֑ק",
    "פֶּן",
    "תֵּצֵ֨א",
    "כָ/אֵ֜שׁ",
    "חֲמָתִ֗/י",
    "וּ/בָעֲרָה֙"
  ],
  "word-count-original": 10,
  "grammatical-notes": {},
  "dictionary-meaning": {},
  "polysemy-log": {},
  "literal-translation": "",
  "main-translation": "",
  "main-translation-explanation": {},
  "rejected-translations": [],
  "rules-applied": [],
  "forensic-confidence": 0
}