{
  "index": 1586,
  "hash": "66d47bdddd8e829192689fc5f76b88bee79cda9ae4f349fd08d043ca5681a41b",
  "source-language": "Hebrew",
  "sentence": "אֲמִילַֽ/ם סַבּ֤וּ/נִי כִ/דְבוֹרִ֗ים דֹּ֭עֲכוּ כְּ/אֵ֣שׁ קוֹצִ֑ים בְּ/שֵׁ֥ם יְ֝הוָ֗ה כִּ֣י אֲמִילַֽ/ם",
  "words": [
    "אֲמִילַֽ/ם",
    "סַבּ֤וּ/נִי",
    "כִ/דְבוֹרִ֗ים",
    "דֹּ֭עֲכוּ",
    "כְּ/אֵ֣שׁ",
    "קוֹצִ֑ים",
    "בְּ/שֵׁ֥ם",
    "יְ֝הוָ֗ה",
    "כִּ֣י",
    "אֲמִילַֽ/ם"
  ],
  "word-count-original": 10,
  "grammatical-notes": {},
  "dictionary-meaning": {},
  "polysemy-log": {},
  "literal-translation": "",
  "main-translation": "",
  "main-translation-explanation": {},
  "rejected-translations": [],
  "rules-applied": [],
  "forensic-confidence": 0
}