{
  "index": 154,
  "hash": "3e43c0904a7613e8a681aff881fdff8654974edf3ff1aadaa561bf19bd27ce73",
  "source-language": "Hebrew",
  "sentence": "מִטַּ֖ת אִ֣ישׁ הָ/אֱלֹהִ֑ים וַ/תִּסְגֹּ֥ר בַּעֲד֖/וֹ וַ/תֵּצֵֽא וַ/תִּקְרָא֮ אֶל אִישָׁ/הּ֒ וַ/תֹּ֗אמֶר",
  "words": [
    "מִטַּ֖ת",
    "אִ֣ישׁ",
    "הָ/אֱלֹהִ֑ים",
    "וַ/תִּסְגֹּ֥ר",
    "בַּעֲד֖/וֹ",
    "וַ/תֵּצֵֽא",
    "וַ/תִּקְרָא֮",
    "אֶל",
    "אִישָׁ/הּ֒",
    "וַ/תֹּ֗אמֶר"
  ],
  "word-count-original": 10,
  "grammatical-notes": {},
  "dictionary-meaning": {},
  "polysemy-log": {},
  "literal-translation": "",
  "main-translation": "",
  "main-translation-explanation": {},
  "rejected-translations": [],
  "rules-applied": [],
  "forensic-confidence": 0
}