{
  "index": 9,
  "hash": "3286028d587e6c3bd5cda225f5f743674b32903627a4efdc1359017087d6624b",
  "source-language": "Greek",
  "sentence": "ἡμέρα Χριστός Ἰησοῦς καθώς εἰμί δίκαιος ἐγώ οὗτος φρονέω ὑπέρ",
  "words": [
    "ἡμέρα",
    "Χριστός",
    "Ἰησοῦς",
    "καθώς",
    "εἰμί",
    "δίκαιος",
    "ἐγώ",
    "οὗτος",
    "φρονέω",
    "ὑπέρ"
  ],
  "word-count-original": 10,
  "grammatical-notes": {},
  "dictionary-meaning": {},
  "polysemy-log": {},
  "literal-translation": "",
  "main-translation": "",
  "main-translation-explanation": {},
  "rejected-translations": [],
  "rules-applied": [],
  "forensic-confidence": 0
}