{
  "index": 1093,
  "hash": "cddb2039955856cd28d2ebf62f0d2df25e59e15e747fa42f1d3b560d46c38658",
  "source-language": "Hebrew",
  "sentence": "סֶֽלָה שְׁמַ֣ע עַ֭מִּ/י וְ/אָעִ֣ידָה בָּ֑/ךְ יִ֝שְׂרָאֵ֗ל אִם תִּֽשְׁמַֽע לִֽ/י לֹֽא",
  "words": [
    "סֶֽלָה",
    "שְׁמַ֣ע",
    "עַ֭מִּ/י",
    "וְ/אָעִ֣ידָה",
    "בָּ֑/ךְ",
    "יִ֝שְׂרָאֵ֗ל",
    "אִם",
    "תִּֽשְׁמַֽע",
    "לִֽ/י",
    "לֹֽא"
  ],
  "word-count-original": 10,
  "grammatical-notes": {},
  "dictionary-meaning": {},
  "polysemy-log": {},
  "literal-translation": "",
  "main-translation": "",
  "main-translation-explanation": {},
  "rejected-translations": [],
  "rules-applied": [],
  "forensic-confidence": 0
}