{
  "index": 79,
  "hash": "87a7a2a85d4df452ef19bd3788bd31fd29d3514c369b5a11ef30d2fdb503684d",
  "source-language": "Greek",
  "sentence": "τις συστατικός ἐπιστολή πρός σύ ἤ ἐκ σύ ὁ ἐπιστολή",
  "words": [
    "τις",
    "συστατικός",
    "ἐπιστολή",
    "πρός",
    "σύ",
    "ἤ",
    "ἐκ",
    "σύ",
    "ὁ",
    "ἐπιστολή"
  ],
  "word-count-original": 10,
  "grammatical-notes": {},
  "dictionary-meaning": {},
  "polysemy-log": {},
  "literal-translation": "",
  "main-translation": "",
  "main-translation-explanation": {},
  "rejected-translations": [],
  "rules-applied": [],
  "forensic-confidence": 0
}