{
  "index": 15,
  "hash": "636ed4b1ea0c81ff2446cf89e17841f6128351f9ec58755c2a79ca50c951b78a",
  "source-language": "Greek",
  "sentence": "ἀντίκειμαι κατά ὁ εὐαγγέλιον ὁ δόξα ὁ μακάριος θεός ὅς",
  "words": [
    "ἀντίκειμαι",
    "κατά",
    "ὁ",
    "εὐαγγέλιον",
    "ὁ",
    "δόξα",
    "ὁ",
    "μακάριος",
    "θεός",
    "ὅς"
  ],
  "word-count-original": 10,
  "grammatical-notes": {},
  "dictionary-meaning": {},
  "polysemy-log": {},
  "literal-translation": "",
  "main-translation": "",
  "main-translation-explanation": {},
  "rejected-translations": [],
  "rules-applied": [],
  "forensic-confidence": 0
}