{
  "index": 446,
  "hash": "b0dce46c0a6db86cfde771578c8aff43747b235f5f2d028f2fcfb2a00ac6d49a",
  "source-language": "Hebrew",
  "sentence": "בַּ/סְּפָרִ֑ים מִסְפַּ֣ר הַ/שָּׁנִ֗ים אֲשֶׁ֨ר הָיָ֤ה דְבַר יְהוָה֙ אֶל יִרְמִיָ֣ה הַ/נָּבִ֔יא",
  "words": [
    "בַּ/סְּפָרִ֑ים",
    "מִסְפַּ֣ר",
    "הַ/שָּׁנִ֗ים",
    "אֲשֶׁ֨ר",
    "הָיָ֤ה",
    "דְבַר",
    "יְהוָה֙",
    "אֶל",
    "יִרְמִיָ֣ה",
    "הַ/נָּבִ֔יא"
  ],
  "word-count-original": 10,
  "grammatical-notes": {},
  "dictionary-meaning": {},
  "polysemy-log": {},
  "literal-translation": "",
  "main-translation": "",
  "main-translation-explanation": {},
  "rejected-translations": [],
  "rules-applied": [],
  "forensic-confidence": 0
}