{
  "index": 467,
  "hash": "6db606e03b74f82b7b2c186a058574c9b1edd457bb886970f892c3ddebb48cc4",
  "source-language": "Hebrew",
  "sentence": "בֹגֵֽד אָמַ֣ר עָ֭צֵל אֲרִ֣י בַ/ח֑וּץ בְּ/ת֥וֹךְ רְ֝חֹב֗וֹת אֵֽרָצֵֽחַ שׁוּחָ֣ה עֲ֭מֻקָּה",
  "words": [
    "בֹגֵֽד",
    "אָמַ֣ר",
    "עָ֭צֵל",
    "אֲרִ֣י",
    "בַ/ח֑וּץ",
    "בְּ/ת֥וֹךְ",
    "רְ֝חֹב֗וֹת",
    "אֵֽרָצֵֽחַ",
    "שׁוּחָ֣ה",
    "עֲ֭מֻקָּה"
  ],
  "word-count-original": 10,
  "grammatical-notes": {},
  "dictionary-meaning": {},
  "polysemy-log": {},
  "literal-translation": "",
  "main-translation": "",
  "main-translation-explanation": {},
  "rejected-translations": [],
  "rules-applied": [],
  "forensic-confidence": 0
}