{
  "index": 1350,
  "hash": "27bf39a5784ae742a695a6214fb155560d6661dd5d4c87f319240d5f5a106436",
  "source-language": "Greek",
  "sentence": "ἀφίημι αὐτός καί λέγω ὁ ἀπόστολος ὁ κύριος προστίθημι ἐγώ",
  "words": [
    "ἀφίημι",
    "αὐτός",
    "καί",
    "λέγω",
    "ὁ",
    "ἀπόστολος",
    "ὁ",
    "κύριος",
    "προστίθημι",
    "ἐγώ"
  ],
  "word-count-original": 10,
  "grammatical-notes": {},
  "dictionary-meaning": {},
  "polysemy-log": {},
  "literal-translation": "",
  "main-translation": "",
  "main-translation-explanation": {},
  "rejected-translations": [],
  "rules-applied": [],
  "forensic-confidence": 0
}