{
  "index": 258,
  "hash": "68a819c59d1cdbad93b70f713a65fc00cc7b542e2c4b1a769e46d7db17d55e8d",
  "source-language": "Hebrew",
  "sentence": "תַּחְתֶּֽי/הָ וַ/יִּשְׁלַ֤ח יְהוֹשֻׁ֨עַ֙ מַלְאָכִ֔ים וַ/יָּרֻ֖צוּ הָ/אֹ֑הֱלָ/ה וְ/הִנֵּ֧ה טְמוּנָ֛ה בְּ/אָהֳל֖/וֹ וְ/הַ/כֶּ֥סֶף",
  "words": [
    "תַּחְתֶּֽי/הָ",
    "וַ/יִּשְׁלַ֤ח",
    "יְהוֹשֻׁ֨עַ֙",
    "מַלְאָכִ֔ים",
    "וַ/יָּרֻ֖צוּ",
    "הָ/אֹ֑הֱלָ/ה",
    "וְ/הִנֵּ֧ה",
    "טְמוּנָ֛ה",
    "בְּ/אָהֳל֖/וֹ",
    "וְ/הַ/כֶּ֥סֶף"
  ],
  "word-count-original": 10,
  "grammatical-notes": {},
  "dictionary-meaning": {},
  "polysemy-log": {},
  "literal-translation": "",
  "main-translation": "",
  "main-translation-explanation": {},
  "rejected-translations": [],
  "rules-applied": [],
  "forensic-confidence": 0
}