{
  "index": 266,
  "hash": "47198907a570d064ae4146956aaa482578cb307f847f39e7c5fa98878ef25a32",
  "source-language": "Hebrew",
  "sentence": "עָלָ֜י/ו גַּל אֲבָנִ֣ים גָּד֗וֹל עַ֚ד הַ/יּ֣וֹם הַ/זֶּ֔ה וַ/יָּ֥שָׁב יְהוָ֖ה מֵ/חֲר֣וֹן",
  "words": [
    "עָלָ֜י/ו",
    "גַּל",
    "אֲבָנִ֣ים",
    "גָּד֗וֹל",
    "עַ֚ד",
    "הַ/יּ֣וֹם",
    "הַ/זֶּ֔ה",
    "וַ/יָּ֥שָׁב",
    "יְהוָ֖ה",
    "מֵ/חֲר֣וֹן"
  ],
  "word-count-original": 10,
  "grammatical-notes": {},
  "dictionary-meaning": {},
  "polysemy-log": {},
  "literal-translation": "",
  "main-translation": "",
  "main-translation-explanation": {},
  "rejected-translations": [],
  "rules-applied": [],
  "forensic-confidence": 0
}