{
  "index": 1248,
  "hash": "4a03b28158bee7b828165e66a350e4e06b55223463536adc62119b08c21c44b6",
  "source-language": "Hebrew",
  "sentence": "אַפִּ֔/י וּ/תְהִלָּתִ֖/י אֶחֱטָם לָ֑/ךְ לְ/בִלְתִּ֖י הַכְרִיתֶֽ/ךָ הִנֵּ֥ה צְרַפְתִּ֖י/ךָ וְ/לֹ֣א בְ/כָ֑סֶף",
  "words": [
    "אַפִּ֔/י",
    "וּ/תְהִלָּתִ֖/י",
    "אֶחֱטָם",
    "לָ֑/ךְ",
    "לְ/בִלְתִּ֖י",
    "הַכְרִיתֶֽ/ךָ",
    "הִנֵּ֥ה",
    "צְרַפְתִּ֖י/ךָ",
    "וְ/לֹ֣א",
    "בְ/כָ֑סֶף"
  ],
  "word-count-original": 10,
  "grammatical-notes": {},
  "dictionary-meaning": {},
  "polysemy-log": {},
  "literal-translation": "",
  "main-translation": "",
  "main-translation-explanation": {},
  "rejected-translations": [],
  "rules-applied": [],
  "forensic-confidence": 0
}