{
  "index": 618,
  "hash": "b6e7751e03c241169a0ef92402fe4d8812e22882d4ed660e7aa0015fa585390f",
  "source-language": "Hebrew",
  "sentence": "הִנֵּ֤ה יְהוָה֙ יֹצֵ֣א מִ/מְּקוֹמ֔/וֹ לִ/פְקֹ֛ד עֲוֺ֥ן יֹֽשֵׁב הָ/אָ֖רֶץ עָלָ֑י/ו וְ/גִלְּתָ֤ה",
  "words": [
    "הִנֵּ֤ה",
    "יְהוָה֙",
    "יֹצֵ֣א",
    "מִ/מְּקוֹמ֔/וֹ",
    "לִ/פְקֹ֛ד",
    "עֲוֺ֥ן",
    "יֹֽשֵׁב",
    "הָ/אָ֖רֶץ",
    "עָלָ֑י/ו",
    "וְ/גִלְּתָ֤ה"
  ],
  "word-count-original": 10,
  "grammatical-notes": {},
  "dictionary-meaning": {},
  "polysemy-log": {},
  "literal-translation": "",
  "main-translation": "",
  "main-translation-explanation": {},
  "rejected-translations": [],
  "rules-applied": [],
  "forensic-confidence": 0
}