{
  "index": 167,
  "hash": "e4c3d02c769d6ce798811bb482cbad712e4bed56b2b207935e98bdb80d3c8312",
  "source-language": "Greek",
  "sentence": "εὔχομαι ὑπέρ ἀλλήλων ὅπως ἰάομαι πολύς ἰσχύω δέησις δίκαιος ἐνεργέω",
  "words": [
    "εὔχομαι",
    "ὑπέρ",
    "ἀλλήλων",
    "ὅπως",
    "ἰάομαι",
    "πολύς",
    "ἰσχύω",
    "δέησις",
    "δίκαιος",
    "ἐνεργέω"
  ],
  "word-count-original": 10,
  "grammatical-notes": {},
  "dictionary-meaning": {},
  "polysemy-log": {},
  "literal-translation": "",
  "main-translation": "",
  "main-translation-explanation": {},
  "rejected-translations": [],
  "rules-applied": [],
  "forensic-confidence": 0
}