{
  "index": 1159,
  "hash": "f613f878c481c525911962f6de75ce5ebf4ac0fdf4c87a9274694e2a35a174a0",
  "source-language": "Hebrew",
  "sentence": "הָ/עָ֔ם לְ/הַשְׁחִ֖ית אֶת הַ/מֶּ֥לֶךְ אֲדֹנֶֽי/ךָ לֹא ט֞וֹב הַ/דָּבָ֣ר הַ/זֶּה֮ אֲשֶׁ֣ר",
  "words": [
    "הָ/עָ֔ם",
    "לְ/הַשְׁחִ֖ית",
    "אֶת",
    "הַ/מֶּ֥לֶךְ",
    "אֲדֹנֶֽי/ךָ",
    "לֹא",
    "ט֞וֹב",
    "הַ/דָּבָ֣ר",
    "הַ/זֶּה֮",
    "אֲשֶׁ֣ר"
  ],
  "word-count-original": 10,
  "grammatical-notes": {},
  "dictionary-meaning": {},
  "polysemy-log": {},
  "literal-translation": "",
  "main-translation": "",
  "main-translation-explanation": {},
  "rejected-translations": [],
  "rules-applied": [],
  "forensic-confidence": 0
}