{
  "index": 874,
  "hash": "12ab352b887f9b284a02fa4aea769dc91eef13bc4642bcf3053db45bd4542b94",
  "source-language": "Hebrew",
  "sentence": "דִבֶּ֥ר שָׁא֛וּל מְא֖וּמָה בַּ/יּ֣וֹם הַ/ה֑וּא כִּ֤י אָמַר֙ מִקְרֶ֣ה ה֔וּא בִּלְתִּ֥י",
  "words": [
    "דִבֶּ֥ר",
    "שָׁא֛וּל",
    "מְא֖וּמָה",
    "בַּ/יּ֣וֹם",
    "הַ/ה֑וּא",
    "כִּ֤י",
    "אָמַר֙",
    "מִקְרֶ֣ה",
    "ה֔וּא",
    "בִּלְתִּ֥י"
  ],
  "word-count-original": 10,
  "grammatical-notes": {},
  "dictionary-meaning": {},
  "polysemy-log": {},
  "literal-translation": "",
  "main-translation": "",
  "main-translation-explanation": {},
  "rejected-translations": [],
  "rules-applied": [],
  "forensic-confidence": 0
}