{
  "index": 272,
  "hash": "5efb0e84093161b58141121eafa28bb80e69b767d11101496974dfb6228c6eec",
  "source-language": "Greek",
  "sentence": "θάπτω πρός ὁ ἀνήρ αὐτός καί γίνομαι φόβος μέγας ἐπί",
  "words": [
    "θάπτω",
    "πρός",
    "ὁ",
    "ἀνήρ",
    "αὐτός",
    "καί",
    "γίνομαι",
    "φόβος",
    "μέγας",
    "ἐπί"
  ],
  "word-count-original": 10,
  "grammatical-notes": {},
  "dictionary-meaning": {},
  "polysemy-log": {},
  "literal-translation": "",
  "main-translation": "",
  "main-translation-explanation": {},
  "rejected-translations": [],
  "rules-applied": [],
  "forensic-confidence": 0
}