{
  "index": 374,
  "hash": "4923e03587a35b824411d6a65288f5ec219d303d8a2b13a9fa721e4d23ff2676",
  "source-language": "Greek",
  "sentence": "περιτομή καί οὕτω(ς) γεννάω ὁ Ἰσαάκ καί περιτέμνω αὐτός ὁ",
  "words": [
    "περιτομή",
    "καί",
    "οὕτω(ς)",
    "γεννάω",
    "ὁ",
    "Ἰσαάκ",
    "καί",
    "περιτέμνω",
    "αὐτός",
    "ὁ"
  ],
  "word-count-original": 10,
  "grammatical-notes": {},
  "dictionary-meaning": {},
  "polysemy-log": {},
  "literal-translation": "",
  "main-translation": "",
  "main-translation-explanation": {},
  "rejected-translations": [],
  "rules-applied": [],
  "forensic-confidence": 0
}