{
  "index": 479,
  "hash": "c2678d18f01c1c282c8b52dd614f5111cc3d575fd8d997efe288e9ba8e3431c0",
  "source-language": "Greek",
  "sentence": "ὁμοθυμαδόν ἐν ὁ ἀκούω αὐτός καί βλέπω ὁ σημεῖον ὅς",
  "words": [
    "ὁμοθυμαδόν",
    "ἐν",
    "ὁ",
    "ἀκούω",
    "αὐτός",
    "καί",
    "βλέπω",
    "ὁ",
    "σημεῖον",
    "ὅς"
  ],
  "word-count-original": 10,
  "grammatical-notes": {},
  "dictionary-meaning": {},
  "polysemy-log": {},
  "literal-translation": "",
  "main-translation": "",
  "main-translation-explanation": {},
  "rejected-translations": [],
  "rules-applied": [],
  "forensic-confidence": 0
}