{
  "index": 558,
  "hash": "6c77321cee90263ec90cdfac72ca12456c432a501caf4f68722dd65831cbbb66",
  "source-language": "Greek",
  "sentence": "ἰδού γάρ προσεύχομαι καί ὁράω ἀνήρ ἐν ὅραμα Ἁνανίας ὄνομα",
  "words": [
    "ἰδού",
    "γάρ",
    "προσεύχομαι",
    "καί",
    "ὁράω",
    "ἀνήρ",
    "ἐν",
    "ὅραμα",
    "Ἁνανίας",
    "ὄνομα"
  ],
  "word-count-original": 10,
  "grammatical-notes": {},
  "dictionary-meaning": {},
  "polysemy-log": {},
  "literal-translation": "",
  "main-translation": "",
  "main-translation-explanation": {},
  "rejected-translations": [],
  "rules-applied": [],
  "forensic-confidence": 0
}