{
  "index": 81,
  "hash": "e77f52d15db08f250ab7fb3c68ffa97af9f06d4dbb6e2f9b2b2743eee62cc5bd",
  "source-language": "Greek",
  "sentence": "ἐγώ ἐν ὁ ἡμέρα ἐκεῖνος ἐκχέω ἀπό ὁ πνεῦμα ἐγώ",
  "words": [
    "ἐγώ",
    "ἐν",
    "ὁ",
    "ἡμέρα",
    "ἐκεῖνος",
    "ἐκχέω",
    "ἀπό",
    "ὁ",
    "πνεῦμα",
    "ἐγώ"
  ],
  "word-count-original": 10,
  "grammatical-notes": {},
  "dictionary-meaning": {},
  "polysemy-log": {},
  "literal-translation": "",
  "main-translation": "",
  "main-translation-explanation": {},
  "rejected-translations": [],
  "rules-applied": [],
  "forensic-confidence": 0
}