{
  "index": 327,
  "hash": "82b8bec4ceac87d815bd1400034315b101df933e3605143367b1adf06dc9c3a7",
  "source-language": "Hebrew",
  "sentence": "סֹ֜לֶת בְּ/שֶׁ֗קֶל וְ/סָאתַ֧יִם שְׂעֹרִ֛ים בְּ/שֶׁ֖קֶל כִּ/דְבַ֥ר יְהוָֽה וְ/הַ/מֶּלֶךְ֩ הִפְקִ֨יד אֶת",
  "words": [
    "סֹ֜לֶת",
    "בְּ/שֶׁ֗קֶל",
    "וְ/סָאתַ֧יִם",
    "שְׂעֹרִ֛ים",
    "בְּ/שֶׁ֖קֶל",
    "כִּ/דְבַ֥ר",
    "יְהוָֽה",
    "וְ/הַ/מֶּלֶךְ֩",
    "הִפְקִ֨יד",
    "אֶת"
  ],
  "word-count-original": 10,
  "grammatical-notes": {},
  "dictionary-meaning": {},
  "polysemy-log": {},
  "literal-translation": "",
  "main-translation": "",
  "main-translation-explanation": {},
  "rejected-translations": [],
  "rules-applied": [],
  "forensic-confidence": 0
}