{
  "index": 476,
  "hash": "9d47f9e4c4a1c4fcd66a1b81fddc41d7d34bdd85a759234cc4ca25b61d1ac66b",
  "source-language": "Hebrew",
  "sentence": "אֶת יָדֶ֑/ךָ וַ/יִּתֵּ֣ן יָד֔/וֹ וַ/יַּעֲלֵ֥/הוּ אֵלָ֖י/ו אֶל הַ/מֶּרְכָּבָֽה וַ/יֹּ֨אמֶר֙ לְכָ֣/ה",
  "words": [
    "אֶת",
    "יָדֶ֑/ךָ",
    "וַ/יִּתֵּ֣ן",
    "יָד֔/וֹ",
    "וַ/יַּעֲלֵ֥/הוּ",
    "אֵלָ֖י/ו",
    "אֶל",
    "הַ/מֶּרְכָּבָֽה",
    "וַ/יֹּ֨אמֶר֙",
    "לְכָ֣/ה"
  ],
  "word-count-original": 10,
  "grammatical-notes": {},
  "dictionary-meaning": {},
  "polysemy-log": {},
  "literal-translation": "",
  "main-translation": "",
  "main-translation-explanation": {},
  "rejected-translations": [],
  "rules-applied": [],
  "forensic-confidence": 0
}