{
  "index": 650,
  "hash": "5a21ed9baf51b3ef485665fcc8ef6831308950aa8315322325418c7f044eb4c7",
  "source-language": "Greek",
  "sentence": "μή φονεύω μή μοιχεύω μή κλέπτω μή ψευδομαρτυρέω μή ἀποστερέω",
  "words": [
    "μή",
    "φονεύω",
    "μή",
    "μοιχεύω",
    "μή",
    "κλέπτω",
    "μή",
    "ψευδομαρτυρέω",
    "μή",
    "ἀποστερέω"
  ],
  "word-count-original": 10,
  "grammatical-notes": {},
  "dictionary-meaning": {},
  "polysemy-log": {},
  "literal-translation": "",
  "main-translation": "",
  "main-translation-explanation": {},
  "rejected-translations": [],
  "rules-applied": [],
  "forensic-confidence": 0
}