{
  "index": 780,
  "hash": "740f85f729a5b659b7a1c044e742cc21a3203565935ca385385b4b727554d6ae",
  "source-language": "Hebrew",
  "sentence": "עֲוֺנ֣/וֹ יִשָּׂ֔א כִּֽי אֶת קֹ֥דֶשׁ יְהוָ֖ה חִלֵּ֑ל וְ/נִכְרְתָ֛ה הַ/נֶּ֥פֶשׁ הַ/הִ֖וא",
  "words": [
    "עֲוֺנ֣/וֹ",
    "יִשָּׂ֔א",
    "כִּֽי",
    "אֶת",
    "קֹ֥דֶשׁ",
    "יְהוָ֖ה",
    "חִלֵּ֑ל",
    "וְ/נִכְרְתָ֛ה",
    "הַ/נֶּ֥פֶשׁ",
    "הַ/הִ֖וא"
  ],
  "word-count-original": 10,
  "grammatical-notes": {},
  "dictionary-meaning": {},
  "polysemy-log": {},
  "literal-translation": "",
  "main-translation": "",
  "main-translation-explanation": {},
  "rejected-translations": [],
  "rules-applied": [],
  "forensic-confidence": 0
}