{
  "index": 210,
  "hash": "95e6f938cb10207453992a6d263a861a542168e2cedd540c949992b5d613cf83",
  "source-language": "Hebrew",
  "sentence": "וְ/חָלְפָ֖ה רַקָּתֽ/וֹ בֵּ֣ין רַגְלֶ֔י/הָ כָּרַ֥ע נָפַ֖ל שָׁכָ֑ב בֵּ֤ין רַגְלֶ֨י/הָ֙ כָּרַ֣ע",
  "words": [
    "וְ/חָלְפָ֖ה",
    "רַקָּתֽ/וֹ",
    "בֵּ֣ין",
    "רַגְלֶ֔י/הָ",
    "כָּרַ֥ע",
    "נָפַ֖ל",
    "שָׁכָ֑ב",
    "בֵּ֤ין",
    "רַגְלֶ֨י/הָ֙",
    "כָּרַ֣ע"
  ],
  "word-count-original": 10,
  "grammatical-notes": {},
  "dictionary-meaning": {},
  "polysemy-log": {},
  "literal-translation": "",
  "main-translation": "",
  "main-translation-explanation": {},
  "rejected-translations": [],
  "rules-applied": [],
  "forensic-confidence": 0
}