{
  "index": 17,
  "hash": "f1a5aa780eccc2a876eaf6a9b1c97693c4878f6367a7a7c7f2ea55548a63ce99",
  "source-language": "Hebrew",
  "sentence": "לֵ/אמֹ֔ר מָ֥ה אַתָּ֖ה רֹאֶ֑ה וָ/אֹמַ֗ר סִ֤יר נָפ֨וּחַ֙ אֲנִ֣י רֹאֶ֔ה וּ/פָנָ֖י/ו",
  "words": [
    "לֵ/אמֹ֔ר",
    "מָ֥ה",
    "אַתָּ֖ה",
    "רֹאֶ֑ה",
    "וָ/אֹמַ֗ר",
    "סִ֤יר",
    "נָפ֨וּחַ֙",
    "אֲנִ֣י",
    "רֹאֶ֔ה",
    "וּ/פָנָ֖י/ו"
  ],
  "word-count-original": 10,
  "grammatical-notes": {},
  "dictionary-meaning": {},
  "polysemy-log": {},
  "literal-translation": "",
  "main-translation": "",
  "main-translation-explanation": {},
  "rejected-translations": [],
  "rules-applied": [],
  "forensic-confidence": 0
}