{
  "index": 1705,
  "hash": "165e65a1db1226ff3849866ac8919d72b924a3abe2aa72d36df2649d55fab29d",
  "source-language": "Hebrew",
  "sentence": "וְ/שָׁ֥ם תָּמֻֽתוּ וְ/יִֽהְי֣וּ כָל הָ/אֲנָשִׁ֗ים אֲשֶׁר שָׂ֨מוּ אֶת פְּנֵי/הֶ֜ם לָ/ב֤וֹא",
  "words": [
    "וְ/שָׁ֥ם",
    "תָּמֻֽתוּ",
    "וְ/יִֽהְי֣וּ",
    "כָל",
    "הָ/אֲנָשִׁ֗ים",
    "אֲשֶׁר",
    "שָׂ֨מוּ",
    "אֶת",
    "פְּנֵי/הֶ֜ם",
    "לָ/ב֤וֹא"
  ],
  "word-count-original": 10,
  "grammatical-notes": {},
  "dictionary-meaning": {},
  "polysemy-log": {},
  "literal-translation": "",
  "main-translation": "",
  "main-translation-explanation": {},
  "rejected-translations": [],
  "rules-applied": [],
  "forensic-confidence": 0
}