{
  "index": 1845,
  "hash": "4b91e4f0e08b63a6615fa605f62e385afde9bb0d99abf14bd95144e0a22b8202",
  "source-language": "Hebrew",
  "sentence": "פוֹקֵד֙ אֶל אָמ֣וֹן מִ/נֹּ֔א וְ/עַל פַּרְעֹה֙ וְ/עַל מִצְרַ֔יִם וְ/עַל אֱלֹהֶ֖י/הָ",
  "words": [
    "פוֹקֵד֙",
    "אֶל",
    "אָמ֣וֹן",
    "מִ/נֹּ֔א",
    "וְ/עַל",
    "פַּרְעֹה֙",
    "וְ/עַל",
    "מִצְרַ֔יִם",
    "וְ/עַל",
    "אֱלֹהֶ֖י/הָ"
  ],
  "word-count-original": 10,
  "grammatical-notes": {},
  "dictionary-meaning": {},
  "polysemy-log": {},
  "literal-translation": "",
  "main-translation": "",
  "main-translation-explanation": {},
  "rejected-translations": [],
  "rules-applied": [],
  "forensic-confidence": 0
}