{
  "index": 402,
  "hash": "3030503f332d99014f5f3dd2fed437dd199f6cdb818993d240d9f33b0798d712",
  "source-language": "Hebrew",
  "sentence": "וְ/כָל מַרְעִיתָ֖/ם נָפֽוֹצָה ק֤וֹל שְׁמוּעָה֙ הִנֵּ֣ה בָאָ֔ה וְ/רַ֥עַשׁ גָּד֖וֹל מֵ/אֶ֣רֶץ",
  "words": [
    "וְ/כָל",
    "מַרְעִיתָ֖/ם",
    "נָפֽוֹצָה",
    "ק֤וֹל",
    "שְׁמוּעָה֙",
    "הִנֵּ֣ה",
    "בָאָ֔ה",
    "וְ/רַ֥עַשׁ",
    "גָּד֖וֹל",
    "מֵ/אֶ֣רֶץ"
  ],
  "word-count-original": 10,
  "grammatical-notes": {},
  "dictionary-meaning": {},
  "polysemy-log": {},
  "literal-translation": "",
  "main-translation": "",
  "main-translation-explanation": {},
  "rejected-translations": [],
  "rules-applied": [],
  "forensic-confidence": 0
}