{
  "index": 843,
  "hash": "d681fd1c2a3177e8e59692c2fcc0c064decfea1807527809021bc4a95221a08e",
  "source-language": "Hebrew",
  "sentence": "מֵ/אֵת֙ נְבִיאֵ֣י יְרוּשָׁלִַ֔ם יָצְאָ֥ה חֲנֻפָּ֖ה לְ/כָל הָ/אָֽרֶץ כֹּֽה אָמַ֞ר יְהוָ֣ה",
  "words": [
    "מֵ/אֵת֙",
    "נְבִיאֵ֣י",
    "יְרוּשָׁלִַ֔ם",
    "יָצְאָ֥ה",
    "חֲנֻפָּ֖ה",
    "לְ/כָל",
    "הָ/אָֽרֶץ",
    "כֹּֽה",
    "אָמַ֞ר",
    "יְהוָ֣ה"
  ],
  "word-count-original": 10,
  "grammatical-notes": {},
  "dictionary-meaning": {},
  "polysemy-log": {},
  "literal-translation": "",
  "main-translation": "",
  "main-translation-explanation": {},
  "rejected-translations": [],
  "rules-applied": [],
  "forensic-confidence": 0
}