{
  "index": 60,
  "hash": "ece04ad4c99b3bcfb18b8769613b9e192976ee50ab7fd1c96a09dabb8fdff212",
  "source-language": "Greek",
  "sentence": "σκεῦος εἰς τιμή ἁγιάζω εὔχρηστος ὁ δεσπότης εἰς πᾶς ἔργον",
  "words": [
    "σκεῦος",
    "εἰς",
    "τιμή",
    "ἁγιάζω",
    "εὔχρηστος",
    "ὁ",
    "δεσπότης",
    "εἰς",
    "πᾶς",
    "ἔργον"
  ],
  "word-count-original": 10,
  "grammatical-notes": {},
  "dictionary-meaning": {},
  "polysemy-log": {},
  "literal-translation": "",
  "main-translation": "",
  "main-translation-explanation": {},
  "rejected-translations": [],
  "rules-applied": [],
  "forensic-confidence": 0
}