{
  "index": 1691,
  "hash": "6264a18dee27b69d3935c2a866bad33418c770e4b47c936f0bb375d684e214cd",
  "source-language": "Greek",
  "sentence": "σύ ὅτι οὐ μή ἐσθίω αὐτός ἕως ὅστις πληρόω ἐν",
  "words": [
    "σύ",
    "ὅτι",
    "οὐ",
    "μή",
    "ἐσθίω",
    "αὐτός",
    "ἕως",
    "ὅστις",
    "πληρόω",
    "ἐν"
  ],
  "word-count-original": 10,
  "grammatical-notes": {},
  "dictionary-meaning": {},
  "polysemy-log": {},
  "literal-translation": "",
  "main-translation": "",
  "main-translation-explanation": {},
  "rejected-translations": [],
  "rules-applied": [],
  "forensic-confidence": 0
}