{
  "index": 85,
  "hash": "d7f5c745a0506a756d097396c3b05e4bc6552c9e3fd5deab683453e661eaa9ee",
  "source-language": "Greek",
  "sentence": "ὁ σπέρμα αὐτός εἰς ὁ αἰών μένω δέ Μαριάμ σύν",
  "words": [
    "ὁ",
    "σπέρμα",
    "αὐτός",
    "εἰς",
    "ὁ",
    "αἰών",
    "μένω",
    "δέ",
    "Μαριάμ",
    "σύν"
  ],
  "word-count-original": 10,
  "grammatical-notes": {},
  "dictionary-meaning": {},
  "polysemy-log": {},
  "literal-translation": "",
  "main-translation": "",
  "main-translation-explanation": {},
  "rejected-translations": [],
  "rules-applied": [],
  "forensic-confidence": 0
}