{
  "index": 972,
  "hash": "88a9366add5dbda54ac9369daba47e6489e1570cd562b0554df0c227555a471c",
  "source-language": "Greek",
  "sentence": "ὁ ἔνειμι δίδωμι ἐλεημοσύνη καί ἰδού πᾶς καθαρός σύ εἰμί",
  "words": [
    "ὁ",
    "ἔνειμι",
    "δίδωμι",
    "ἐλεημοσύνη",
    "καί",
    "ἰδού",
    "πᾶς",
    "καθαρός",
    "σύ",
    "εἰμί"
  ],
  "word-count-original": 10,
  "grammatical-notes": {},
  "dictionary-meaning": {},
  "polysemy-log": {},
  "literal-translation": "",
  "main-translation": "",
  "main-translation-explanation": {},
  "rejected-translations": [],
  "rules-applied": [],
  "forensic-confidence": 0
}