{
  "index": 585,
  "hash": "f8b984457354c29a2792023cac0c00b5c425e89f3b5f268d5e5ca2c8f6a9c173",
  "source-language": "Greek",
  "sentence": "ἄρα ὁ κήρυγμα ἐγώ κενός καί ὁ πίστις σύ εὑρίσκω",
  "words": [
    "ἄρα",
    "ὁ",
    "κήρυγμα",
    "ἐγώ",
    "κενός",
    "καί",
    "ὁ",
    "πίστις",
    "σύ",
    "εὑρίσκω"
  ],
  "word-count-original": 10,
  "grammatical-notes": {},
  "dictionary-meaning": {},
  "polysemy-log": {},
  "literal-translation": "",
  "main-translation": "",
  "main-translation-explanation": {},
  "rejected-translations": [],
  "rules-applied": [],
  "forensic-confidence": 0
}