{
  "index": 644,
  "hash": "89c2ab794fb510cf62e57fc4566b1f8e92369125870682cb95fdefecd755acba",
  "source-language": "Greek",
  "sentence": "νῖκος ποῦ σύ θάνατος ὁ κέντρον ὁ δέ κέντρον ὁ",
  "words": [
    "νῖκος",
    "ποῦ",
    "σύ",
    "θάνατος",
    "ὁ",
    "κέντρον",
    "ὁ",
    "δέ",
    "κέντρον",
    "ὁ"
  ],
  "word-count-original": 10,
  "grammatical-notes": {},
  "dictionary-meaning": {},
  "polysemy-log": {},
  "literal-translation": "",
  "main-translation": "",
  "main-translation-explanation": {},
  "rejected-translations": [],
  "rules-applied": [],
  "forensic-confidence": 0
}