{
  "index": 71,
  "hash": "70313684471fc1d85fd17fe9c5ec6dea4ed8c4039269beefe63db1e02890491b",
  "source-language": "Greek",
  "sentence": "ἐγώ δέ οὐ ὁ πνεῦμα ὁ κόσμος λαμβάνω ἀλλά ὁ",
  "words": [
    "ἐγώ",
    "δέ",
    "οὐ",
    "ὁ",
    "πνεῦμα",
    "ὁ",
    "κόσμος",
    "λαμβάνω",
    "ἀλλά",
    "ὁ"
  ],
  "word-count-original": 10,
  "grammatical-notes": {},
  "dictionary-meaning": {},
  "polysemy-log": {},
  "literal-translation": "",
  "main-translation": "",
  "main-translation-explanation": {},
  "rejected-translations": [],
  "rules-applied": [],
  "forensic-confidence": 0
}