{
  "index": 1100,
  "hash": "13b0cd821d9b9da61699a8f36475392f52d212f891d77fccce6fe31f57e5fbde",
  "source-language": "Greek",
  "sentence": "ὅς λέγω σύ εἰρήνη ἀφίημι σύ εἰρήνη ὁ ἐμός δίδωμι",
  "words": [
    "ὅς",
    "λέγω",
    "σύ",
    "εἰρήνη",
    "ἀφίημι",
    "σύ",
    "εἰρήνη",
    "ὁ",
    "ἐμός",
    "δίδωμι"
  ],
  "word-count-original": 10,
  "grammatical-notes": {},
  "dictionary-meaning": {},
  "polysemy-log": {},
  "literal-translation": "",
  "main-translation": "",
  "main-translation-explanation": {},
  "rejected-translations": [],
  "rules-applied": [],
  "forensic-confidence": 0
}