{
  "index": 1117,
  "hash": "5c774faa912aa9a186abd6e01e167896d1b5720f1c40073e99a7fa8d4df138c4",
  "source-language": "Greek",
  "sentence": "μένω ἐγώ εἰμί ὁ ἄμπελος σύ ὁ κλῆμα ὁ μένω",
  "words": [
    "μένω",
    "ἐγώ",
    "εἰμί",
    "ὁ",
    "ἄμπελος",
    "σύ",
    "ὁ",
    "κλῆμα",
    "ὁ",
    "μένω"
  ],
  "word-count-original": 10,
  "grammatical-notes": {},
  "dictionary-meaning": {},
  "polysemy-log": {},
  "literal-translation": "",
  "main-translation": "",
  "main-translation-explanation": {},
  "rejected-translations": [],
  "rules-applied": [],
  "forensic-confidence": 0
}