{
  "index": 106,
  "hash": "6557bdab275b80e8839729194499c77510bfc290a802f2d076456d30d7fe8be8",
  "source-language": "Hebrew",
  "sentence": "מִשְׂפָּ֔ח לִ/צְדָקָ֖ה וְ/הִנֵּ֥ה צְעָקָֽה ה֗וֹי מַגִּיעֵ֥י בַ֨יִת֙ בְּ/בַ֔יִת שָׂדֶ֥ה בְ/שָׂדֶ֖ה",
  "words": [
    "מִשְׂפָּ֔ח",
    "לִ/צְדָקָ֖ה",
    "וְ/הִנֵּ֥ה",
    "צְעָקָֽה",
    "ה֗וֹי",
    "מַגִּיעֵ֥י",
    "בַ֨יִת֙",
    "בְּ/בַ֔יִת",
    "שָׂדֶ֥ה",
    "בְ/שָׂדֶ֖ה"
  ],
  "word-count-original": 10,
  "grammatical-notes": {},
  "dictionary-meaning": {},
  "polysemy-log": {},
  "literal-translation": "",
  "main-translation": "",
  "main-translation-explanation": {},
  "rejected-translations": [],
  "rules-applied": [],
  "forensic-confidence": 0
}