{
  "index": 1126,
  "hash": "86a70ae7d1a436df7f1b44f63191aa10620cd4127798e63c3ba06b543139d661",
  "source-language": "Hebrew",
  "sentence": "בֽ/וֹ כֹּה אָמַ֨ר יְהוָ֥ה עֹשֶׂ֛/ךָ וְ/יֹצֶרְ/ךָ֥ מִ/בֶּ֖טֶן יַעְזְרֶ֑/ךָּ אַל תִּירָא֙",
  "words": [
    "בֽ/וֹ",
    "כֹּה",
    "אָמַ֨ר",
    "יְהוָ֥ה",
    "עֹשֶׂ֛/ךָ",
    "וְ/יֹצֶרְ/ךָ֥",
    "מִ/בֶּ֖טֶן",
    "יַעְזְרֶ֑/ךָּ",
    "אַל",
    "תִּירָא֙"
  ],
  "word-count-original": 10,
  "grammatical-notes": {},
  "dictionary-meaning": {},
  "polysemy-log": {},
  "literal-translation": "",
  "main-translation": "",
  "main-translation-explanation": {},
  "rejected-translations": [],
  "rules-applied": [],
  "forensic-confidence": 0
}