{
  "index": 630,
  "hash": "840062f0e4a1fb67dfca9f7613ca7cce03dd1059aa02992f784b8a5ecb45dd72",
  "source-language": "Greek",
  "sentence": "ζῳοποιέω ἀλλά οὐ πρῶτος ὁ πνευματικός ἀλλά ὁ ψυχικός ἔπειτα",
  "words": [
    "ζῳοποιέω",
    "ἀλλά",
    "οὐ",
    "πρῶτος",
    "ὁ",
    "πνευματικός",
    "ἀλλά",
    "ὁ",
    "ψυχικός",
    "ἔπειτα"
  ],
  "word-count-original": 10,
  "grammatical-notes": {},
  "dictionary-meaning": {},
  "polysemy-log": {},
  "literal-translation": "",
  "main-translation": "",
  "main-translation-explanation": {},
  "rejected-translations": [],
  "rules-applied": [],
  "forensic-confidence": 0
}